quantum_hydra.py
quantum_hydra_cipher-3.0.0.dist-info/licenses/LICENSE
quantum_hydra_cipher-3.0.0.dist-info/METADATA
quantum_hydra_cipher-3.0.0.dist-info/WHEEL
quantum_hydra_cipher-3.0.0.dist-info/entry_points.txt
quantum_hydra_cipher-3.0.0.dist-info/top_level.txt
quantum_hydra_cipher-3.0.0.dist-info/RECORD
