Metadata-Version: 2.4
Name: quantum-hydra-cipher
Version: 3.0.0
Summary: A 7-layer encryption system supporting multiple file formats
Home-page: https://github.com/yourusername/quantum-hydra
Author: Muhammad Sufiyan Baig
Author-email: Muhammad Sufiyan Baig <send.sufiyan@gmail.com>
Maintainer-email: Muhammad Sufiyan Baig <send.sufiyan@gmail.com>
License: MIT
Project-URL: Homepage, https://github.com/yourusername/quantum-hydra
Project-URL: Documentation, https://github.com/yourusername/quantum-hydra#readme
Project-URL: Repository, https://github.com/yourusername/quantum-hydra.git
Project-URL: Bug Reports, https://github.com/yourusername/quantum-hydra/issues
Project-URL: Changelog, https://github.com/yourusername/quantum-hydra/blob/main/CHANGELOG.md
Keywords: encryption,cipher,security,cryptography,multi-layer,file-encryption,pdf,image,video,audio
Classifier: Development Status :: 4 - Beta
Classifier: Intended Audience :: Developers
Classifier: Intended Audience :: End Users/Desktop
Classifier: Topic :: Security :: Cryptography
Classifier: License :: OSI Approved :: MIT License
Classifier: Programming Language :: Python :: 3
Classifier: Programming Language :: Python :: 3.8
Classifier: Programming Language :: Python :: 3.9
Classifier: Programming Language :: Python :: 3.10
Classifier: Programming Language :: Python :: 3.11
Classifier: Programming Language :: Python :: 3.12
Classifier: Operating System :: OS Independent
Classifier: Environment :: Console
Requires-Python: >=3.8
License-File: LICENSE
Dynamic: author
Dynamic: home-page
Dynamic: license-file
Dynamic: requires-python
